{
    "Titel": [
        "BWp7",
        "Advanced Petrology",
        "Vertiefung Petrologie",
        "Wahlpflichtmodul ",
        "8 CP = 240 h",
        "8 SWS"
    ],
    "Inhalte": "In diesem Modul werden petrologische Konzepte vermittelt, die die Interpretation der Genese und Entwicklung von magmatischen, metamorphen und sedimentären Gesteinen erlauben. Neben theoretischen Aspekten werden praktische Arbeitsweisen, wie z.B. die Bestimmung des Mineralbestandes von Gesteinen und deren Gefüge mittels Polarisationsmikroskopie, vermittelt. Darüber hinaus werden durch Übungsaufgaben quantitative Methoden der Petrologie eingeführt.\nIn \"Spezielle Themen der Petrologie\" werden abwechselnd unterschiedliche petrologisch relevante Themen vertieft.",
    "Lernergebnisse / Kompetenzziele": "Die Studierenden vertiefen ihre Kompetenzen in der Interpretation von Gesteinen. Dies erfolgt vor allem durch: \n* das Beobachten und Beschreiben (makroskopisch und mikroskopisch) von Gesteinen\n* das Erlernen von neuen Methoden zur chemischen und physikalischen Quantifizierung von Gesteinen\n* die Auswertung von Daten aus Fallbeispielen, einschlieálich durch Berechnungen\n* die Betrachtung und Bewertung von Modellen für die Entstehung und Entwicklung von Gesteinen\n* Die Studierenden lernen verschiedene quantitative Methoden der modernen Petrologie anzuwenden",
    "Teilnahmevoraussetzungen für Modul bzw. für einzelne Lehrveranstaltungen des Moduls": "bzw. für einzelne Lehrveranstaltungen des Moduls\n\nAbgeschlossenes Modul BP2 \"Geomaterialien\nTeilnahme an den Modulen BP4 \"Mineralogie\" und \"BP7 \"Petrologie\"",
    "Empfohlene Voraussetzungen": "-",
    "Organisatorische Hinweise": "Aus dem Angebot sind Veranstaltungen im Umfang von mind. 8 CP zu belegen.",
    "Zuordnung des Moduls (Studiengang / Fachbereich)": "(Studiengang / Fachbereich)\nB.Sc. Geowissenschaften / FB11",
    "Verwendbarkeit des Moduls für andere Studiengänge": "für andere Studiengänge \nB.Sc./M.Sc. Chemie",
    "Häufigkeit des Angebots": "jährlich",
    "Dauer des Moduls": "2 Semester",
    "Modulbeauftragte / Modulbeauftragter": "Prof. Dr. Alan B. Woodland",
    "Studiennachweise/ ggf. als Prüfungsvorleistungen": "Teilnahmenachweise \n-\n\nLeistungsnachweise\nErfolgreiche Teilnahme an \"Spezielle Themen der Petrologie\"",
    "Lehr- / Lernformen": "Vorlesung, Übung",
    "Unterrichts- / Prüfungssprache": "Deutsch, Englisch",
    "Modulprüfung": "Form / Dauer / ggf. Inhalt\n\nModulabschlussprüfung \nbestehend aus:\nKlausur (120 min) aus den 2 gewählten 3-stündigen Veranstaltungen\n\nkumulative Modulprüfung bestehend aus:\n-\n\nBildung der Modulnote bei kumulativen Modulprüfungen:\n-\n\n\nLV-Form\nSWS\nCP\nSemester\n\n\n\n\n\n1\n2\n3\n4\n5\n6\n\nAuswahl aus:\n\n\n\n\n\n\n\n\n\n\nPetrologie der \nmagmatischen Gesteine \nV+Ü\n3\n3\n\n\n\n\n\nX\n\nPetrologie der \nmetamorphen Gesteine\nV+Ü\n3\n3\n\n\n\n\n\nX\n\nPetrologie und Diagenese der Sedimentgesteine\nV+Ü\n3\n3\n\n\n\n\nX\n\n\nSpezielle Themen der \nPetrologie\nV\n2\n2\n\n\n\n\nX\nX\n\nModulprüfung\nKlausur\n\n\n\n\n\n\nX\nX\n\nSumme:\n\n8 - 9\n8 - 9\n\n\nB",
    "Übersicht": {
        "Veranstaltung": [
            "SWS",
            "",
            "1",
            "5",
            "",
            "",
            "",
            "V+Ü",
            "",
            "X",
            "V+Ü",
            "",
            "X",
            "3",
            "",
            "",
            "2",
            "",
            "",
            "",
            ""
        ],
        "LV-Form": [
            "CP",
            "",
            "2",
            "6",
            "",
            "",
            "",
            "3",
            "",
            "",
            "3",
            "",
            "",
            "3",
            "",
            "Spezielle Themen der",
            "2",
            "",
            "Modulprüfung",
            "",
            "X"
        ],
        "SWS": [
            "Semester",
            "",
            "3",
            "",
            "",
            "",
            "Petrologie der",
            "3",
            "",
            "Petrologie der",
            "3",
            "",
            "Petrologie und Diagenese der Sedimentgesteine",
            "",
            "X",
            "Petrologie",
            "",
            "X",
            "Klausur",
            "",
            "X"
        ],
        "CP": [
            "",
            "",
            "4",
            "Auswahl aus:",
            "",
            "",
            "magmatischen Gesteine",
            "",
            "",
            "metamorphen Gesteine",
            "",
            "",
            "V+Ü",
            "",
            "",
            "V",
            "",
            "X",
            "",
            "",
            ""
        ],
        "Semester": [
            [],
            [],
            [],
            [],
            [],
            []
        ]
    },
    "Prüfung": "Platz für alles mögliche",
    "Version": [
        "2023-10-13",
        "2023-04-04",
        "2022-07-11",
        "2021-01-01"
    ],
    "Änderung": {
        "2023-10-13": "PL in SL geändert",
        "2023-04-04": "Neuer Modulbeauftragter",
        "2022-07-11": "Neuen Kurs xx eingefügt",
        "2021-01-01": "CP um einen erhöht"
    }
}